[
    {
        "id": 1,
        "teilnehmer_id": 2,
        "zeitpunkt": "2026-01-21 15:35:00",
        "reflexionsgrad": 0.54963,
        "meta_kohaerenz": 0.848357,
        "selbstbezug_index": 0,
        "reflexions_marker": "mittel",
        "bemerkung": "Reflexionsgrad: 0.55 | Meta-Kohärenz: 0.85 | Selbstbezug: 0.00 | Stabilität: 0.92"
    },
    {
        "id": 2,
        "teilnehmer_id": 3,
        "zeitpunkt": "2025-11-25 15:35:00",
        "reflexionsgrad": 0.562778,
        "meta_kohaerenz": 0.850092,
        "selbstbezug_index": 0,
        "reflexions_marker": "mittel",
        "bemerkung": "Reflexionsgrad: 0.56 | Meta-Kohärenz: 0.85 | Selbstbezug: 0.00 | Stabilität: 0.94"
    },
    {
        "id": 3,
        "teilnehmer_id": 4,
        "zeitpunkt": "2025-11-28 15:35:00",
        "reflexionsgrad": 0.560074,
        "meta_kohaerenz": 0.723089,
        "selbstbezug_index": 0,
        "reflexions_marker": "mittel",
        "bemerkung": "Reflexionsgrad: 0.56 | Meta-Kohärenz: 0.72 | Selbstbezug: 0.00 | Stabilität: 0.93"
    },
    {
        "id": 4,
        "teilnehmer_id": 5,
        "zeitpunkt": "2025-12-10 18:27:20",
        "reflexionsgrad": 0.51063,
        "meta_kohaerenz": 0.816034,
        "selbstbezug_index": 0,
        "reflexions_marker": "mittel",
        "bemerkung": "Reflexionsgrad: 0.51 | Meta-Kohärenz: 0.82 | Selbstbezug: 0.00 | Stabilität: 0.85"
    },
    {
        "id": 5,
        "teilnehmer_id": 6,
        "zeitpunkt": "2026-01-21 15:35:00",
        "reflexionsgrad": 0.584312,
        "meta_kohaerenz": 0.843524,
        "selbstbezug_index": 0,
        "reflexions_marker": "mittel",
        "bemerkung": "Reflexionsgrad: 0.58 | Meta-Kohärenz: 0.84 | Selbstbezug: 0.00 | Stabilität: 0.97"
    },
    {
        "id": 6,
        "teilnehmer_id": 7,
        "zeitpunkt": "2025-12-10 17:10:00",
        "reflexionsgrad": 0.499926,
        "meta_kohaerenz": 0.70656,
        "selbstbezug_index": 0,
        "reflexions_marker": "mittel",
        "bemerkung": "Reflexionsgrad: 0.50 | Meta-Kohärenz: 0.71 | Selbstbezug: 0.00 | Stabilität: 0.83"
    },
    {
        "id": 7,
        "teilnehmer_id": 8,
        "zeitpunkt": "2025-12-09 17:10:00",
        "reflexionsgrad": 0.553278,
        "meta_kohaerenz": 0.695395,
        "selbstbezug_index": 0,
        "reflexions_marker": "mittel",
        "bemerkung": "Reflexionsgrad: 0.55 | Meta-Kohärenz: 0.70 | Selbstbezug: 0.00 | Stabilität: 0.92"
    },
    {
        "id": 8,
        "teilnehmer_id": 9,
        "zeitpunkt": "2025-12-11 16:48:38",
        "reflexionsgrad": 0.473103,
        "meta_kohaerenz": 0.617235,
        "selbstbezug_index": 0,
        "reflexions_marker": "mittel",
        "bemerkung": "Reflexionsgrad: 0.47 | Meta-Kohärenz: 0.62 | Selbstbezug: 0.00 | Stabilität: 0.79"
    },
    {
        "id": 9,
        "teilnehmer_id": 10,
        "zeitpunkt": "2025-12-11 15:35:00",
        "reflexionsgrad": 0.543936,
        "meta_kohaerenz": 0.838271,
        "selbstbezug_index": 0,
        "reflexions_marker": "mittel",
        "bemerkung": "Reflexionsgrad: 0.54 | Meta-Kohärenz: 0.84 | Selbstbezug: 0.00 | Stabilität: 0.91"
    },
    {
        "id": 10,
        "teilnehmer_id": 11,
        "zeitpunkt": "2026-01-21 15:35:00",
        "reflexionsgrad": 0.554972,
        "meta_kohaerenz": 0.758322,
        "selbstbezug_index": 0,
        "reflexions_marker": "mittel",
        "bemerkung": "Reflexionsgrad: 0.55 | Meta-Kohärenz: 0.76 | Selbstbezug: 0.00 | Stabilität: 0.92"
    },
    {
        "id": 11,
        "teilnehmer_id": 12,
        "zeitpunkt": "2025-12-10 17:10:00",
        "reflexionsgrad": 0.588542,
        "meta_kohaerenz": 0.990186,
        "selbstbezug_index": 0,
        "reflexions_marker": "mittel",
        "bemerkung": "Reflexionsgrad: 0.59 | Meta-Kohärenz: 0.99 | Selbstbezug: 0.00 | Stabilität: 0.98"
    },
    {
        "id": 12,
        "teilnehmer_id": 13,
        "zeitpunkt": "2025-11-12 17:10:00",
        "reflexionsgrad": 0.547467,
        "meta_kohaerenz": 0.855868,
        "selbstbezug_index": 0,
        "reflexions_marker": "mittel",
        "bemerkung": "Reflexionsgrad: 0.55 | Meta-Kohärenz: 0.86 | Selbstbezug: 0.00 | Stabilität: 0.91"
    },
    {
        "id": 13,
        "teilnehmer_id": 14,
        "zeitpunkt": "2025-12-10 17:10:00",
        "reflexionsgrad": 0.558518,
        "meta_kohaerenz": 0.734721,
        "selbstbezug_index": 0,
        "reflexions_marker": "mittel",
        "bemerkung": "Reflexionsgrad: 0.56 | Meta-Kohärenz: 0.73 | Selbstbezug: 0.00 | Stabilität: 0.93"
    },
    {
        "id": 14,
        "teilnehmer_id": 15,
        "zeitpunkt": "2025-12-11 16:52:16",
        "reflexionsgrad": 0.387727,
        "meta_kohaerenz": 0.430365,
        "selbstbezug_index": 0,
        "reflexions_marker": "mittel",
        "bemerkung": "Reflexionsgrad: 0.39 | Meta-Kohärenz: 0.43 | Selbstbezug: 0.00 | Stabilität: 0.65"
    },
    {
        "id": 15,
        "teilnehmer_id": 16,
        "zeitpunkt": "2026-01-15 17:10:00",
        "reflexionsgrad": 0.495773,
        "meta_kohaerenz": 0.790025,
        "selbstbezug_index": 0,
        "reflexions_marker": "mittel",
        "bemerkung": "Reflexionsgrad: 0.50 | Meta-Kohärenz: 0.79 | Selbstbezug: 0.00 | Stabilität: 0.83"
    },
    {
        "id": 16,
        "teilnehmer_id": 17,
        "zeitpunkt": "2025-12-11 17:10:00",
        "reflexionsgrad": 0.406296,
        "meta_kohaerenz": 0.791654,
        "selbstbezug_index": 0,
        "reflexions_marker": "mittel",
        "bemerkung": "Reflexionsgrad: 0.41 | Meta-Kohärenz: 0.79 | Selbstbezug: 0.00 | Stabilität: 0.68"
    },
    {
        "id": 17,
        "teilnehmer_id": 18,
        "zeitpunkt": "2026-01-15 17:10:00",
        "reflexionsgrad": 0.513909,
        "meta_kohaerenz": 0.779933,
        "selbstbezug_index": 0,
        "reflexions_marker": "mittel",
        "bemerkung": "Reflexionsgrad: 0.51 | Meta-Kohärenz: 0.78 | Selbstbezug: 0.00 | Stabilität: 0.86"
    },
    {
        "id": 18,
        "teilnehmer_id": 19,
        "zeitpunkt": "2026-01-15 17:10:00",
        "reflexionsgrad": 0.576867,
        "meta_kohaerenz": 0.844959,
        "selbstbezug_index": 0,
        "reflexions_marker": "mittel",
        "bemerkung": "Reflexionsgrad: 0.58 | Meta-Kohärenz: 0.84 | Selbstbezug: 0.00 | Stabilität: 0.96"
    },
    {
        "id": 19,
        "teilnehmer_id": 20,
        "zeitpunkt": "2026-01-16 15:35:00",
        "reflexionsgrad": 0.549167,
        "meta_kohaerenz": 0.97439,
        "selbstbezug_index": 0,
        "reflexions_marker": "mittel",
        "bemerkung": "Reflexionsgrad: 0.55 | Meta-Kohärenz: 0.97 | Selbstbezug: 0.00 | Stabilität: 0.92"
    },
    {
        "id": 20,
        "teilnehmer_id": 21,
        "zeitpunkt": "2025-12-08 17:10:00",
        "reflexionsgrad": 0.486385,
        "meta_kohaerenz": 0.809868,
        "selbstbezug_index": 0,
        "reflexions_marker": "mittel",
        "bemerkung": "Reflexionsgrad: 0.49 | Meta-Kohärenz: 0.81 | Selbstbezug: 0.00 | Stabilität: 0.81"
    },
    {
        "id": 21,
        "teilnehmer_id": 22,
        "zeitpunkt": "2025-12-11 17:10:00",
        "reflexionsgrad": 0.461089,
        "meta_kohaerenz": 0.774692,
        "selbstbezug_index": 0,
        "reflexions_marker": "mittel",
        "bemerkung": "Reflexionsgrad: 0.46 | Meta-Kohärenz: 0.77 | Selbstbezug: 0.00 | Stabilität: 0.77"
    },
    {
        "id": 22,
        "teilnehmer_id": 23,
        "zeitpunkt": "2025-12-08 17:10:00",
        "reflexionsgrad": 0.569633,
        "meta_kohaerenz": 0.977769,
        "selbstbezug_index": 0,
        "reflexions_marker": "mittel",
        "bemerkung": "Reflexionsgrad: 0.57 | Meta-Kohärenz: 0.98 | Selbstbezug: 0.00 | Stabilität: 0.95"
    },
    {
        "id": 23,
        "teilnehmer_id": 24,
        "zeitpunkt": "2026-01-16 15:35:00",
        "reflexionsgrad": 0.551833,
        "meta_kohaerenz": 0.710331,
        "selbstbezug_index": 0,
        "reflexions_marker": "mittel",
        "bemerkung": "Reflexionsgrad: 0.55 | Meta-Kohärenz: 0.71 | Selbstbezug: 0.00 | Stabilität: 0.92"
    },
    {
        "id": 24,
        "teilnehmer_id": 40,
        "zeitpunkt": "2025-11-10 15:35:00",
        "reflexionsgrad": 0.4238,
        "meta_kohaerenz": 0.932644,
        "selbstbezug_index": 0,
        "reflexions_marker": "mittel",
        "bemerkung": "Reflexionsgrad: 0.42 | Meta-Kohärenz: 0.93 | Selbstbezug: 0.00 | Stabilität: 0.71"
    },
    {
        "id": 25,
        "teilnehmer_id": 42,
        "zeitpunkt": "2025-12-11 15:35:00",
        "reflexionsgrad": 0.580697,
        "meta_kohaerenz": 0.229151,
        "selbstbezug_index": 0,
        "reflexions_marker": "mittel",
        "bemerkung": "Reflexionsgrad: 0.58 | Meta-Kohärenz: 0.23 | Selbstbezug: 0.00 | Stabilität: 0.97"
    },
    {
        "id": 26,
        "teilnehmer_id": 43,
        "zeitpunkt": "2026-01-19 15:35:00",
        "reflexionsgrad": 0.55437,
        "meta_kohaerenz": 0.977145,
        "selbstbezug_index": 0,
        "reflexions_marker": "mittel",
        "bemerkung": "Reflexionsgrad: 0.55 | Meta-Kohärenz: 0.98 | Selbstbezug: 0.00 | Stabilität: 0.92"
    },
    {
        "id": 27,
        "teilnehmer_id": 45,
        "zeitpunkt": "2025-12-09 17:10:00",
        "reflexionsgrad": 0.501333,
        "meta_kohaerenz": 0.987144,
        "selbstbezug_index": 0,
        "reflexions_marker": "mittel",
        "bemerkung": "Reflexionsgrad: 0.50 | Meta-Kohärenz: 0.99 | Selbstbezug: 0.00 | Stabilität: 0.84"
    },
    {
        "id": 28,
        "teilnehmer_id": 47,
        "zeitpunkt": "2025-12-09 18:29:00",
        "reflexionsgrad": 0.478667,
        "meta_kohaerenz": 1,
        "selbstbezug_index": 0,
        "reflexions_marker": "mittel",
        "bemerkung": "Reflexionsgrad: 0.48 | Meta-Kohärenz: 1.00 | Selbstbezug: 0.00 | Stabilität: 0.80"
    }
]